{
    "name": "海报墙默认",
    "engine": "海报墙",
    "config": {
        "engine": "海报墙",
        "badge_style": "box",
        "badge_font": "剑豪体.ttf",
        "badge_size": "80",
        "badge_bg_color": "#262931",
        "badge_text_color": "#ffffff",
        "badge_opacity": "170",
        "title": "欧美电影",
        "subtitle": "Western Movies",
        "font_title": "剑豪体.ttf",
        "font_subtitle": "剑豪体.ttf",
        "poster_count": "40",
        "col_count": "10",
        "poster_ratio": 1.5,
        "brightness": "0.4",
        "bar_height": 300,
        "bar_opacity": "170",
        "bar_color": "#000000",
        "line_color": "#000000",
        "line_width": 4,
        "title_size": 140,
        "title_color": "#FFFFFF",
        "title_offset_y": "-130",
        "subtitle_size": "80",
        "subtitle_color": "#CCCCCC",
        "subtitle_offset_y": "40",
        "text_width_percent": "100",
        "badge_border_opacity": "14"
    }
}